secured_fields/__init__.py
secured_fields/apps.py
secured_fields/enum.py
secured_fields/exceptions.py
secured_fields/fernet.py
secured_fields/fields/__init__.py
secured_fields/fields/files.py
secured_fields/lookups.py
secured_fields/management/commands/generate_key.py
secured_fields/mixins.py
secured_fields/storage.py
secured_fields/utils.py
django_secured_fields-0.4.4.dist-info/LICENSE
django_secured_fields-0.4.4.dist-info/METADATA
django_secured_fields-0.4.4.dist-info/WHEEL
django_secured_fields-0.4.4.dist-info/RECORD
