Metadata-Version: 2.1
Name: django-secured-fields
Version: 0.4.4
Summary: 
Home-page: https://github.com/C0D1UM/django-secured-fields
License: MIT
Keywords: django,encrypted,fields,drf,django-rest,restframework,search,encryption,hash
Author: CODIUM
Author-email: support@codium.co
Requires-Python: >=3.8,<4.0
Classifier: License :: OSI Approved :: MIT License
Classifier: Programming Language :: Python :: 3
Classifier: Programming Language :: Python :: 3.8
Classifier: Programming Language :: Python :: 3.9
Classifier: Programming Language :: Python :: 3.10
Classifier: Programming Language :: Python :: 3.11
Classifier: Programming Language :: Python :: 3.12
Requires-Dist: cryptography (>=35)
Requires-Dist: django (>=3.1)
Project-URL: Repository, https://github.com/C0D1UM/django-secured-fields
